waifu_pics/__init__.py
waifu_pics/__main__.py
waifu_pics/constants.py
waifu_pics/waifu.py
waifu_pics-1.0.1.dist-info/LICENSE
waifu_pics-1.0.1.dist-info/METADATA
waifu_pics-1.0.1.dist-info/WHEEL
waifu_pics-1.0.1.dist-info/entry_points.txt
waifu_pics-1.0.1.dist-info/top_level.txt
waifu_pics-1.0.1.dist-info/RECORD
