Metadata-Version: 2.1
Name: waifu-pics
Version: 1.0.1
Summary: A simple command line app to open a waifu image/gif on the browser. This is a wrapper for the [waifu.pics](https://waifu.pics/docs) API.
Home-page: https://github.com/diptangsu/waifu-pics
Author: Diptangsu Goswami
Author-email: diptangsu.97@gmail.com
License: MIT
Platform: UNKNOWN
Classifier: License :: OSI Approved :: MIT License
Classifier: Programming Language :: Python :: 3
Classifier: Programming Language :: Python :: 3.8
